[{"monthKey": "November 09, 2019", "pageUrl": "/livescores/3206723", "id": "3206723", "home": {"name": "Dulwich Hamlet", "id": "282508"}, "away": {"name": "Carlisle United", "id": "10196"}, "status": {"finished": true, "started": true, "cancelled": false, "scoreStr": "1 : 4", "startDateStr": "Nov 9, 2019", "reason": {"short": "FT", "long": "Full-Time"}}, "firstUnplayedMatch": false}, {"monthKey": "November 09, 2019", "pageUrl": "/livescores/3206722", "id": "3206722", "home": {"name": "Sunderland", "id": "8472"}, "away": {"name": "Gillingham", "id": "10173"}, "status": {"finished": true, "started": true, "cancelled": false, "scoreStr": "1 : 1", "startDateStr": "Nov 9, 2019", "reason": {"short": "FT", "long": "Full-Time"}}, "firstUnplayedMatch": false}, {"monthKey": "November 09, 2019", "pageUrl": "/livescores/3206742", "id": "3206742", "home": {"name": "Accrington Stanley", "id": "8671"}, "away": {"name": "Crewe Alexandra", "id": "9784"}, "status": {"finished": true, "started": true, "cancelled": false, "scoreStr": "0 : 2", "startDateStr": "Nov 9, 2019", "reason": {"short": "FT", "long": "Full-Time"}}, "firstUnplayedMatch": false}, {"monthKey": "November 09, 2019", "pageUrl": "/livescores/3206733", "id": "3206733", "home": {"name": "AFC Wimbledon", "id": "158319"}, "away": {"name": "Doncaster Rovers", "id": "9903"}, "status": {"finished": true, "started": true, "cancelled": false, "scoreStr": "1 : 1", "startDateStr": "Nov 9, 2019", "reason": {"short": "FT", "long": "Full-Time"}}, "firstUnplayedMatch": false}, {"monthKey": "November 09, 2019", "pageUrl": "/livescores/3206744", "id": "3206744", "home": {"name": "Blackpool", "id": "8483"}, "away": {"name": "Morecambe", "id": "8489"}, "status": {"finished": true, "started": true, "cancelled": false, "scoreStr": "4 : 1", "startDateStr": "Nov 9, 2019", "reason": {"short": "FT", "long": "Full-Time"}}, "firstUnplayedMatch": false}, {"monthKey": "November 09, 2019", "pageUrl": "/livescores/3206724", "id": "3206724", "home": {"name": "Bolton Wanderers", "id": "8559"}, "away": {"name": "Plymouth Argyle", "id": "8401"}, "status": {"finished": true, "started": true, "cancelled": false, "scoreStr": "0 : 1", "startDateStr": "Nov 9, 2019", "reason": {"short": "FT", "long": "Full-Time"}}, "firstUnplayedMatch": false}, {"monthKey": "November 09, 2019", "pageUrl": "/livescores/3206728", "id": "3206728", "home": {"name": "Cambridge United", "id": "9834"}, "away": {"name": "Exeter City", "id": "9833"}, "status": {"finished": true, "started": true, "cancelled": false, "scoreStr": "1 : 1", "startDateStr": "Nov 9, 2019", "reason": {"short": "FT", "long": "Full-Time"}}, "firstUnplayedMatch": false}, {"monthKey": "November 09, 2019", "pageUrl": "/livescores/3206740", "id": "3206740", "home": {"name": "Carshalton Athletic", "id": "161809"}, "away": {"name": "Boston United", "id": "8646"}, "status": {"finished": true, "started": true, "cancelled": false, "scoreStr": "1 : 4", "startDateStr": "Nov 9, 2019", "reason": {"short": "FT", "long": "Full-Time"}}, "firstUnplayedMatch": false}, {"monthKey": "November 09, 2019", "pageUrl": "/livescores/3206741", "id": "3206741", "home": {"name": "Cheltenham Town", "id": "8680"}, "away": {"name": "Swindon Town", "id": "9795"}, "status": {"finished": true, "started": true, "cancelled": false, "scoreStr": "1 : 1", "startDateStr": "Nov 9, 2019", "reason": {"short": "FT", "long": "Full-Time"}}, "firstUnplayedMatch": false}, {"monthKey": "November 09, 2019", "pageUrl": "/livescores/3206721", "id": "3206721", "home": {"name": "Colchester United", "id": "8416"}, "away": {"name": "Coventry City", "id": "8669"}, "status": {"finished": true, "started": true, "cancelled": false, "scoreStr": "0 : 2", "startDateStr": "Nov 9, 2019", "reason": {"short": "FT", "long": "Full-Time"}}, "firstUnplayedMatch": false}, {"monthKey": "November 09, 2019", "pageUrl": "/livescores/3206719", "id": "3206719", "home": {"name": "Crawley Town", "id": "8647"}, "away": {"name": "Scunthorpe United", "id": "8412"}, "status": {"finished": true, "started": true, "cancelled": false, "scoreStr": "4 : 1", "startDateStr": "Nov 9, 2019", "reason": {"short": "FT", "long": "Full-Time"}}, "firstUnplayedMatch": false}, {"monthKey": "November 09, 2019", "pageUrl": "/livescores/3207571", "id": "3207571", "home": {"name": "Ebbsfleet United", "id": "9794"}, "away": {"name": "Notts County", "id": "9819"}, "status": {"finished": true, "started": true, "cancelled": false, "scoreStr": "2 : 3", "startDateStr": "Nov 9, 2019", "reason": {"short": "FT", "long": "Full-Time"}}, "firstUnplayedMatch": false}, {"monthKey": "November 09, 2019", "pageUrl": "/livescores/3207573", "id": "3207573", "home": {"name": "Forest Green Rovers", "id": "9828"}, "away": {"name": "Billericay", "id": "2261"}, "status": {"finished": true, "started": true, "cancelled": false, "scoreStr": "4 : 0", "startDateStr": "Nov 9, 2019", "reason": {"short": "FT", "long": "Full-Time"}}, "firstUnplayedMatch": false}, {"monthKey": "November 09, 2019", "pageUrl": "/livescores/3206735", "id": "3206735", "home": {"name": "Grimsby Town", "id": "10005"}, "away": {"name": "Newport County", "id": "10262"}, "status": {"finished": true, "started": true, "cancelled": false, "scoreStr": "1 : 1", "startDateStr": "Nov 9, 2019", "reason": {"short": "FT", "long": "Full-Time"}}, "firstUnplayedMatch": false}, {"monthKey": "November 09, 2019", "pageUrl": "/livescores/3207572", "id": "3207572", "home": {"name": "Maidenhead United", "id": "45725"}, "away": {"name": "Rotherham United", "id": "8119"}, "status": {"finished": true, "started": true, "cancelled": false, "scoreStr": "1 : 3", "startDateStr": "Nov 9, 2019", "reason": {"short": "FT", "long": "Full-Time"}}, "firstUnplayedMatch": false}, {"monthKey": "November 09, 2019", "pageUrl": "/livescores/3206725", "id": "3206725", "home": {"name": "Maidstone", "id": "8131"}, "away": {"name": "Torquay United", "id": "10193"}, "status": {"finished": true, "started": true, "cancelled": false, "scoreStr": "1 : 0", "startDateStr": "Nov 9, 2019", "reason": {"short": "FT", "long": "Full-Time"}}, "firstUnplayedMatch": false}, {"monthKey": "November 09, 2019", "pageUrl": "/livescores/3206737", "id": "3206737", "home": {"name": "Mansfield Town", "id": "9818"}, "away": {"name": "Chorley", "id": "274599"}, "status": {"finished": true, "started": true, "cancelled": false, "scoreStr": "1 : 0", "startDateStr": "Nov 9, 2019", "reason": {"short": "FT", "long": "Full-Time"}}, "firstUnplayedMatch": false}, {"monthKey": "November 09, 2019", "pageUrl": "/livescores/3206745", "id": "3206745", "home": {"name": "Milton Keynes Dons", "id": "8645"}, "away": {"name": "Port Vale", "id": "9799"}, "status": {"finished": true, "started": true, "cancelled": false, "scoreStr": "0 : 1", "startDateStr": "Nov 9, 2019", "reason": {"short": "FT", "long": "Full-Time"}}, "firstUnplayedMatch": false}, {"monthKey": "November 09, 2019", "pageUrl": "/livescores/3206732", "id": "3206732", "home": {"name": "Nantwich Town", "id": "161821"}, "away": {"name": "AFC Fylde", "id": "282396"}, "status": {"finished": true, "started": true, "cancelled": false, "scoreStr": "0 : 1", "startDateStr": "Nov 9, 2019", "reason": {"short": "FT", "long": "Full-Time"}}, "firstUnplayedMatch": false}, {"monthKey": "November 09, 2019", "pageUrl": "/livescores/3206718", "id": "3206718", "home": {"name": "Oxford City", "id": "161836"}, "away": {"name": "Solihull Moors", "id": "161801"}, "status": {"finished": true, "started": true, "cancelled": false, "scoreStr": "1 : 5", "startDateStr": "Nov 9, 2019", "reason": {"short": "FT", "long": "Full-Time"}}, "firstUnplayedMatch": false}, {"monthKey": "November 09, 2019", "pageUrl": "/livescores/3206729", "id": "3206729", "home": {"name": "Salford City", "id": "282326"}, "away": {"name": "Burton Albion", "id": "9792"}, "status": {"finished": true, "started": true, "cancelled": false, "scoreStr": "1 : 1", "startDateStr": "Nov 9, 2019", "reason": {"short": "FT", "long": "Full-Time"}}, "firstUnplayedMatch": false}, {"monthKey": "November 09, 2019", "pageUrl": "/livescores/3206734", "id": "3206734", "home": {"name": "Shrewsbury Town", "id": "9896"}, "away": {"name": "Bradford City", "id": "8484"}, "status": {"finished": true, "started": true, "cancelled": false, "scoreStr": "1 : 1", "startDateStr": "Nov 9, 2019", "reason": {"short": "FT", "long": "Full-Time"}}, "firstUnplayedMatch": false}, {"monthKey": "November 09, 2019", "pageUrl": "/livescores/3206746", "id": "3206746", "home": {"name": "Stevenage", "id": "10253"}, "away": {"name": "Peterborough United", "id": "8677"}, "status": {"finished": true, "started": true, "cancelled": false, "scoreStr": "1 : 1", "startDateStr": "Nov 9, 2019", "reason": {"short": "FT", "long": "Full-Time"}}, "firstUnplayedMatch": false}, {"monthKey": "November 09, 2019", "pageUrl": "/livescores/3207569", "id": "3207569", "home": {"name": "Stourbridge", "id": "161834"}, "away": {"name": "Eastleigh", "id": "161803"}, "status": {"finished": true, "started": true, "cancelled": false, "scoreStr": "2 : 2", "startDateStr": "Nov 9, 2019", "reason": {"short": "FT", "long": "Full-Time"}}, "firstUnplayedMatch": false}, {"monthKey": "November 09, 2019", "pageUrl": "/livescores/3206739", "id": "3206739", "home": {"name": "Tranmere Rovers", "id": "8313"}, "away": {"name": "Wycombe Wanderers", "id": "8676"}, "status": {"finished": true, "started": true, "cancelled": false, "scoreStr": "2 : 2", "startDateStr": "Nov 9, 2019", "reason": {"short": "FT", "long": "Full-Time"}}, "firstUnplayedMatch": false}, {"monthKey": "November 09, 2019", "pageUrl": "/livescores/3206731", "id": "3206731", "home": {"name": "Walsall", "id": "10006"}, "away": {"name": "Darlington", "id": "8598"}, "status": {"finished": true, "started": true, "cancelled": false, "scoreStr": "2 : 2", "startDateStr": "Nov 9, 2019", "reason": {"short": "FT", "long": "Full-Time"}}, "firstUnplayedMatch": false}, {"monthKey": "November 09, 2019", "pageUrl": "/livescores/3206717", "id": "3206717", "home": {"name": "Ipswich Town", "id": "9902"}, "away": {"name": "Lincoln City", "id": "8430"}, "status": {"finished": true, "started": true, "cancelled": false, "scoreStr": "1 : 1", "startDateStr": "Nov 9, 2019", "reason": {"short": "FT", "long": "Full-Time"}}, "firstUnplayedMatch": false}, {"monthKey": "November 10, 2019", "pageUrl": "/livescores/3206738", "id": "3206738", "home": {"name": "Dover Athletic", "id": "4454"}, "away": {"name": "Southend United", "id": "8652"}, "status": {"finished": true, "started": true, "cancelled": false, "scoreStr": "1 : 0", "startDateStr": "Nov 10, 2019", "reason": {"short": "FT", "long": "Full-Time"}}, "firstUnplayedMatch": false}, {"monthKey": "November 10, 2019", "pageUrl": "/livescores/3207575", "id": "3207575", "home": {"name": "Barnet", "id": "8175"}, "away": {"name": "Fleetwood Town", "id": "45723"}, "status": {"finished": true, "started": true, "cancelled": false, "scoreStr": "0 : 2", "startDateStr": "Nov 10, 2019", "reason": {"short": "FT", "long": "Full-Time"}}, "firstUnplayedMatch": false}, {"monthKey": "November 10, 2019", "pageUrl": "/livescores/3206730", "id": "3206730", "home": {"name": "Bristol Rovers", "id": "10104"}, "away": {"name": "Bromley", "id": "45729"}, "status": {"finished": true, "started": true, "cancelled": false, "scoreStr": "1 : 1", "startDateStr": "Nov 10, 2019", "reason": {"short": "FT", "long": "Full-Time"}}, "firstUnplayedMatch": false}, {"monthKey": "November 10, 2019", "pageUrl": "/livescores/3206727", "id": "3206727", "home": {"name": "Chippenham Town", "id": "7962"}, "away": {"name": "Northampton Town", "id": "8651"}, "status": {"finished": true, "started": true, "cancelled": false, "scoreStr": "0 : 3", "startDateStr": "Nov 10, 2019", "reason": {"short": "FT", "long": "Full-Time"}}, "firstUnplayedMatch": false}, {"monthKey": "November 10, 2019", "pageUrl": "/livescores/3206736", "id": "3206736", "home": {"name": "Gateshead FC", "id": "6189"}, "away": {"name": "Oldham Athletic", "id": "9785"}, "status": {"finished": true, "started": true, "cancelled": false, "scoreStr": "1 : 2", "startDateStr": "Nov 10, 2019", "reason": {"short": "FT", "long": "Full-Time"}}, "firstUnplayedMatch": false}, {"monthKey": "November 10, 2019", "pageUrl": "/livescores/3206726", "id": "3206726", "home": {"name": "Leyton Orient", "id": "8351"}, "away": {"name": "Maldon & Tiptree", "id": "282501"}, "status": {"finished": true, "started": true, "cancelled": false, "scoreStr": "1 : 2", "startDateStr": "Nov 10, 2019", "reason": {"short": "FT", "long": "Full-Time"}}, "firstUnplayedMatch": false}, {"monthKey": "November 10, 2019", "pageUrl": "/livescores/3206743", "id": "3206743", "home": {"name": "Macclesfield Town", "id": "8599"}, "away": {"name": "Kingstonian", "id": "6449"}, "status": {"finished": true, "started": true, "cancelled": false, "scoreStr": "0 : 4", "startDateStr": "Nov 10, 2019", "reason": {"short": "FT", "long": "Full-Time"}}, "firstUnplayedMatch": false}, {"monthKey": "November 10, 2019", "pageUrl": "/livescores/3207570", "id": "3207570", "home": {"name": "Wrexham", "id": "9841"}, "away": {"name": "Rochdale", "id": "8493"}, "status": {"finished": true, "started": true, "cancelled": false, "scoreStr": "0 : 0", "startDateStr": "Nov 10, 2019", "reason": {"short": "FT", "long": "Full-Time"}}, "firstUnplayedMatch": false}, {"monthKey": "November 10, 2019", "pageUrl": "/livescores/3206747", "id": "3206747", "home": {"name": "York City", "id": "9916"}, "away": {"name": "Altrincham", "id": "9915"}, "status": {"finished": true, "started": true, "cancelled": false, "scoreStr": "0 : 1", "startDateStr": "Nov 10, 2019", "reason": {"short": "FT", "long": "Full-Time"}}, "firstUnplayedMatch": false}, {"monthKey": "November 10, 2019", "pageUrl": "/livescores/3207574", "id": "3207574", "home": {"name": "Hayes & Yeading United", "id": "8656"}, "away": {"name": "Oxford United", "id": "8653"}, "status": {"finished": true, "started": true, "cancelled": false, "scoreStr": "0 : 2", "startDateStr": "Nov 10, 2019", "reason": {"short": "FT", "long": "Full-Time"}}, "firstUnplayedMatch": false}, {"monthKey": "November 12, 2019", "pageUrl": "/livescores/3206720", "id": "3206720", "home": {"name": "Harrogate", "id": "7946"}, "away": {"name": "Portsmouth", "id": "8462"}, "status": {"finished": true, "started": true, "cancelled": false, "scoreStr": "1 : 2", "startDateStr": "Nov 12, 2019", "reason": {"short": "FT", "long": "Full-Time"}}, "firstUnplayedMatch": false}, {"monthKey": "November 13, 2019", "pageUrl": "/livescores/3207576", "id": "3207576", "home": {"name": "Yeovil Town", "id": "10198"}, "away": {"name": "Hartlepool United", "id": "8488"}, "status": {"finished": true, "started": true, "cancelled": false, "scoreStr": "1 : 4", "startDateStr": "Nov 13, 2019", "reason": {"short": "FT", "long": "Full-Time"}}, "firstUnplayedMatch": false}, {"monthKey": "November 20, 2019", "pageUrl": "/livescores/3218334", "id": "3218334", "home": {"name": "Bradford City", "id": "8484"}, "away": {"name": "Shrewsbury Town", "id": "9896"}, "status": {"finished": true, "started": true, "cancelled": false, "scoreStr": "0 : 1", "startDateStr": "Nov 20, 2019", "reason": {"short": "FT", "long": "Full-Time"}}, "firstUnplayedMatch": false}, {"monthKey": "November 20, 2019", "pageUrl": "/livescores/3218649", "id": "3218649", "home": {"name": "Bromley", "id": "45729"}, "away": {"name": "Bristol Rovers", "id": "10104"}, "status": {"finished": true, "started": true, "cancelled": false, "scoreStr": "0 : 1", "startDateStr": "Nov 20, 2019", "reason": {"short": "FT", "long": "Full-Time"}}, "firstUnplayedMatch": false}, {"monthKey": "November 20, 2019", "pageUrl": "/livescores/3218332", "id": "3218332", "home": {"name": "Burton Albion", "id": "9792"}, "away": {"name": "Salford City", "id": "282326"}, "status": {"finished": true, "started": true, "cancelled": false, "scoreStr": "4 : 1", "startDateStr": "Nov 20, 2019", "reason": {"short": "FT", "long": "Full-Time"}}, "firstUnplayedMatch": false}, {"monthKey": "November 20, 2019", "pageUrl": "/livescores/3218331", "id": "3218331", "home": {"name": "Eastleigh", "id": "161803"}, "away": {"name": "Stourbridge", "id": "161834"}, "status": {"finished": true, "started": true, "cancelled": false, "scoreStr": "3 : 0", "startDateStr": "Nov 20, 2019", "reason": {"short": "FT", "long": "Full-Time"}}, "firstUnplayedMatch": false}, {"monthKey": "November 20, 2019", "pageUrl": "/livescores/3218330", "id": "3218330", "home": {"name": "Exeter City", "id": "9833"}, "away": {"name": "Cambridge United", "id": "9834"}, "status": {"finished": true, "started": true, "cancelled": false, "scoreStr": "1 : 0", "startDateStr": "Nov 20, 2019", "reason": {"short": "FT", "long": "Full-Time"}}, "firstUnplayedMatch": false}, {"monthKey": "November 20, 2019", "pageUrl": "/livescores/3218329", "id": "3218329", "home": {"name": "Gillingham", "id": "10173"}, "away": {"name": "Sunderland", "id": "8472"}, "status": {"finished": true, "started": true, "cancelled": false, "scoreStr": "1 : 0", "startDateStr": "Nov 20, 2019", "reason": {"short": "FT", "long": "Full-Time"}}, "firstUnplayedMatch": false}, {"monthKey": "November 20, 2019", "pageUrl": "/livescores/3218337", "id": "3218337", "home": {"name": "Peterborough United", "id": "8677"}, "away": {"name": "Stevenage", "id": "10253"}, "status": {"finished": true, "started": true, "cancelled": false, "scoreStr": "2 : 0", "startDateStr": "Nov 20, 2019", "reason": {"short": "FT", "long": "Full-Time"}}, "firstUnplayedMatch": false}, {"monthKey": "November 20, 2019", "pageUrl": "/livescores/3218648", "id": "3218648", "home": {"name": "Rochdale", "id": "8493"}, "away": {"name": "Wrexham", "id": "9841"}, "status": {"finished": true, "started": true, "cancelled": false, "scoreStr": "1 : 0", "startDateStr": "Nov 20, 2019", "reason": {"short": "FT", "long": "Full-Time"}}, "firstUnplayedMatch": false}, {"monthKey": "November 20, 2019", "pageUrl": "/livescores/3218336", "id": "3218336", "home": {"name": "Swindon Town", "id": "9795"}, "away": {"name": "Cheltenham Town", "id": "8680"}, "status": {"finished": true, "started": true, "cancelled": false, "scoreStr": "0 : 1", "startDateStr": "Nov 20, 2019", "reason": {"short": "FT", "long": "Full-Time"}}, "firstUnplayedMatch": false}, {"monthKey": "November 20, 2019", "pageUrl": "/livescores/3218333", "id": "3218333", "home": {"name": "Doncaster Rovers", "id": "9903"}, "away": {"name": "AFC Wimbledon", "id": "158319"}, "status": {"finished": true, "started": true, "cancelled": false, "scoreStr": "2 : 0", "startDateStr": "Nov 20, 2019", "reason": {"short": "FT", "long": "Full-Time"}}, "firstUnplayedMatch": false}, {"monthKey": "November 21, 2019", "pageUrl": "/livescores/3218338", "id": "3218338", "home": {"name": "Darlington", "id": "8598"}, "away": {"name": "Walsall", "id": "10006"}, "status": {"finished": true, "started": true, "cancelled": false, "scoreStr": "0 : 1", "startDateStr": "Nov 21, 2019", "reason": {"short": "FT", "long": "Full-Time"}}, "firstUnplayedMatch": false}, {"monthKey": "November 21, 2019", "pageUrl": "/livescores/3218328", "id": "3218328", "home": {"name": "Lincoln City", "id": "8430"}, "away": {"name": "Ipswich Town", "id": "9902"}, "status": {"finished": true, "started": true, "cancelled": false, "scoreStr": "0 : 1", "startDateStr": "Nov 21, 2019", "reason": {"short": "FT", "long": "Full-Time"}}, "firstUnplayedMatch": false}, {"monthKey": "November 21, 2019", "pageUrl": "/livescores/3218335", "id": "3218335", "home": {"name": "Newport County", "id": "10262"}, "away": {"name": "Grimsby Town", "id": "10005"}, "status": {"finished": true, "started": true, "cancelled": false, "scoreStr": "2 : 0", "startDateStr": "Nov 21, 2019", "reason": {"short": "FT", "long": "Full-Time"}}, "firstUnplayedMatch": false}, {"monthKey": "November 21, 2019", "pageUrl": "/livescores/3218339", "id": "3218339", "home": {"name": "Wycombe Wanderers", "id": "8676"}, "away": {"name": "Tranmere Rovers", "id": "8313"}, "status": {"finished": true, "started": true, "cancelled": false, "scoreStr": "1 : 2", "startDateStr": "Nov 21, 2019", "reason": {"short": "FT", "long": "Full-Time"}}, "firstUnplayedMatch": false}, {"monthKey": "November 30, 2019", "pageUrl": "/livescores/3219000", "id": "3219000", "home": {"name": "Maldon & Tiptree", "id": "282501"}, "away": {"name": "Newport County", "id": "10262"}, "status": {"finished": true, "started": true, "cancelled": false, "scoreStr": "0 : 1", "startDateStr": "Nov 30, 2019", "reason": {"short": "FT", "long": "Full-Time"}}, "firstUnplayedMatch": false}, {"monthKey": "November 30, 2019", "pageUrl": "/livescores/3219002", "id": "3219002", "home": {"name": "Cheltenham Town", "id": "8680"}, "away": {"name": "Port Vale", "id": "9799"}, "status": {"finished": true, "started": true, "cancelled": false, "scoreStr": "1 : 3", "startDateStr": "Nov 30, 2019", "reason": {"short": "FT", "long": "Full-Time"}}, "firstUnplayedMatch": false}, {"monthKey": "November 30, 2019", "pageUrl": "/livescores/3218994", "id": "3218994", "home": {"name": "Forest Green Rovers", "id": "9828"}, "away": {"name": "Carlisle United", "id": "10196"}, "status": {"finished": true, "started": true, "cancelled": false, "scoreStr": "2 : 2", "startDateStr": "Nov 30, 2019", "reason": {"short": "FT", "long": "Full-Time"}}, "firstUnplayedMatch": false}, {"monthKey": "November 30, 2019", "pageUrl": "/livescores/3218990", "id": "3218990", "home": {"name": "Kingstonian", "id": "6449"}, "away": {"name": "AFC Fylde", "id": "282396"}, "status": {"finished": true, "started": true, "cancelled": false, "scoreStr": "0 : 2", "startDateStr": "Nov 30, 2019", "reason": {"short": "FT", "long": "Full-Time"}}, "firstUnplayedMatch": false}, {"monthKey": "November 30, 2019", "pageUrl": "/livescores/3218999", "id": "3218999", "home": {"name": "Oldham Athletic", "id": "9785"}, "away": {"name": "Burton Albion", "id": "9792"}, "status": {"finished": true, "started": true, "cancelled": false, "scoreStr": "0 : 1", "startDateStr": "Nov 30, 2019", "reason": {"short": "FT", "long": "Full-Time"}}, "firstUnplayedMatch": false}, {"monthKey": "November 30, 2019", "pageUrl": "/livescores/3219005", "id": "3219005", "home": {"name": "Portsmouth", "id": "8462"}, "away": {"name": "Altrincham", "id": "9915"}, "status": {"finished": true, "started": true, "cancelled": false, "scoreStr": "2 : 1", "startDateStr": "Nov 30, 2019", "reason": {"short": "FT", "long": "Full-Time"}}, "firstUnplayedMatch": false}, {"monthKey": "November 30, 2019", "pageUrl": "/livescores/3218988", "id": "3218988", "home": {"name": "Shrewsbury Town", "id": "9896"}, "away": {"name": "Mansfield Town", "id": "9818"}, "status": {"finished": true, "started": true, "cancelled": false, "scoreStr": "2 : 0", "startDateStr": "Nov 30, 2019", "reason": {"short": "FT", "long": "Full-Time"}}, "firstUnplayedMatch": false}, {"monthKey": "November 30, 2019", "pageUrl": "/livescores/3218992", "id": "3218992", "home": {"name": "Walsall", "id": "10006"}, "away": {"name": "Oxford United", "id": "8653"}, "status": {"finished": true, "started": true, "cancelled": false, "scoreStr": "0 : 1", "startDateStr": "Nov 30, 2019", "reason": {"short": "FT", "long": "Full-Time"}}, "firstUnplayedMatch": false}, {"monthKey": "November 30, 2019", "pageUrl": "/livescores/3218993", "id": "3218993", "home": {"name": "Eastleigh", "id": "161803"}, "away": {"name": "Crewe Alexandra", "id": "9784"}, "status": {"finished": true, "started": true, "cancelled": false, "scoreStr": "1 : 1", "startDateStr": "Nov 30, 2019", "reason": {"short": "FT", "long": "Full-Time"}}, "firstUnplayedMatch": false}, {"monthKey": "December 01, 2019", "pageUrl": "/livescores/3218987", "id": "3218987", "home": {"name": "Blackpool", "id": "8483"}, "away": {"name": "Maidstone", "id": "8131"}, "status": {"finished": true, "started": true, "cancelled": false, "scoreStr": "3 : 1", "startDateStr": "Dec 1, 2019", "reason": {"short": "FT", "long": "Full-Time"}}, "firstUnplayedMatch": false}, {"monthKey": "December 01, 2019", "pageUrl": "/livescores/3219004", "id": "3219004", "home": {"name": "Bristol Rovers", "id": "10104"}, "away": {"name": "Plymouth Argyle", "id": "8401"}, "status": {"finished": true, "started": true, "cancelled": false, "scoreStr": "1 : 1", "startDateStr": "Dec 1, 2019", "reason": {"short": "FT", "long": "Full-Time"}}, "firstUnplayedMatch": false}, {"monthKey": "December 01, 2019", "pageUrl": "/livescores/3218989", "id": "3218989", "home": {"name": "Coventry City", "id": "8669"}, "away": {"name": "Ipswich Town", "id": "9902"}, "status": {"finished": true, "started": true, "cancelled": false, "scoreStr": "1 : 1", "startDateStr": "Dec 1, 2019", "reason": {"short": "FT", "long": "Full-Time"}}, "firstUnplayedMatch": false}, {"monthKey": "December 01, 2019", "pageUrl": "/livescores/3219001", "id": "3219001", "home": {"name": "Crawley Town", "id": "8647"}, "away": {"name": "Fleetwood Town", "id": "45723"}, "status": {"finished": true, "started": true, "cancelled": false, "scoreStr": "1 : 2", "startDateStr": "Dec 1, 2019", "reason": {"short": "FT", "long": "Full-Time"}}, "firstUnplayedMatch": false}, {"monthKey": "December 01, 2019", "pageUrl": "/livescores/3219006", "id": "3219006", "home": {"name": "Exeter City", "id": "9833"}, "away": {"name": "Hartlepool United", "id": "8488"}, "status": {"finished": true, "started": true, "cancelled": false, "scoreStr": "2 : 2", "startDateStr": "Dec 1, 2019", "reason": {"short": "FT", "long": "Full-Time"}}, "firstUnplayedMatch": false}, {"monthKey": "December 01, 2019", "pageUrl": "/livescores/3218996", "id": "3218996", "home": {"name": "Gillingham", "id": "10173"}, "away": {"name": "Doncaster Rovers", "id": "9903"}, "status": {"finished": true, "started": true, "cancelled": false, "scoreStr": "3 : 0", "startDateStr": "Dec 1, 2019", "reason": {"short": "FT", "long": "Full-Time"}}, "firstUnplayedMatch": false}, {"monthKey": "December 01, 2019", "pageUrl": "/livescores/3219003", "id": "3219003", "home": {"name": "Northampton Town", "id": "8651"}, "away": {"name": "Notts County", "id": "9819"}, "status": {"finished": true, "started": true, "cancelled": false, "scoreStr": "3 : 1", "startDateStr": "Dec 1, 2019", "reason": {"short": "FT", "long": "Full-Time"}}, "firstUnplayedMatch": false}, {"monthKey": "December 01, 2019", "pageUrl": "/livescores/3218998", "id": "3218998", "home": {"name": "Peterborough United", "id": "8677"}, "away": {"name": "Dover Athletic", "id": "4454"}, "status": {"finished": true, "started": true, "cancelled": false, "scoreStr": "3 : 0", "startDateStr": "Dec 1, 2019", "reason": {"short": "FT", "long": "Full-Time"}}, "firstUnplayedMatch": false}, {"monthKey": "December 01, 2019", "pageUrl": "/livescores/3218997", "id": "3218997", "home": {"name": "Rochdale", "id": "8493"}, "away": {"name": "Boston United", "id": "8646"}, "status": {"finished": true, "started": true, "cancelled": false, "scoreStr": "0 : 0", "startDateStr": "Dec 1, 2019", "reason": {"short": "FT", "long": "Full-Time"}}, "firstUnplayedMatch": false}, {"monthKey": "December 01, 2019", "pageUrl": "/livescores/3218991", "id": "3218991", "home": {"name": "Tranmere Rovers", "id": "8313"}, "away": {"name": "Chichester City FC", "id": "1071515"}, "status": {"finished": true, "started": true, "cancelled": false, "scoreStr": "5 : 1", "startDateStr": "Dec 1, 2019", "reason": {"short": "FT", "long": "Full-Time"}}, "firstUnplayedMatch": false}, {"monthKey": "December 03, 2019", "pageUrl": "/livescores/3218995", "id": "3218995", "home": {"name": "Solihull Moors", "id": "161801"}, "away": {"name": "Rotherham United", "id": "8119"}, "status": {"finished": true, "started": true, "cancelled": false, "scoreStr": "3 : 4", "startDateStr": "Dec 3, 2019", "reason": {"short": "FT", "long": "Full-Time"}}, "firstUnplayedMatch": false}, {"monthKey": "December 11, 2019", "pageUrl": "/livescores/3230779", "id": "3230779", "home": {"name": "Carlisle United", "id": "10196"}, "away": {"name": "Forest Green Rovers", "id": "9828"}, "status": {"finished": true, "started": true, "cancelled": false, "scoreStr": "1 : 0", "startDateStr": "Dec 11, 2019", "reason": {"short": "FT", "long": "Full-Time"}}, "firstUnplayedMatch": false}, {"monthKey": "December 11, 2019", "pageUrl": "/livescores/3230778", "id": "3230778", "home": {"name": "Crewe Alexandra", "id": "9784"}, "away": {"name": "Eastleigh", "id": "161803"}, "status": {"finished": true, "started": true, "cancelled": false, "scoreStr": "3 : 1", "startDateStr": "Dec 11, 2019", "reason": {"short": "FT", "long": "Full-Time"}}, "firstUnplayedMatch": false}, {"monthKey": "December 11, 2019", "pageUrl": "/livescores/3230798", "id": "3230798", "home": {"name": "Hartlepool United", "id": "8488"}, "away": {"name": "Exeter City", "id": "9833"}, "status": {"finished": true, "started": true, "cancelled": false, "scoreStr": "1 : 0", "startDateStr": "Dec 11, 2019", "reason": {"short": "FT", "long": "Full-Time"}}, "firstUnplayedMatch": false}, {"monthKey": "December 11, 2019", "pageUrl": "/livescores/3230797", "id": "3230797", "home": {"name": "Ipswich Town", "id": "9902"}, "away": {"name": "Coventry City", "id": "8669"}, "status": {"finished": true, "started": true, "cancelled": false, "scoreStr": "1 : 2", "startDateStr": "Dec 11, 2019", "reason": {"short": "FT", "long": "Full-Time"}}, "firstUnplayedMatch": false}, {"monthKey": "December 17, 2019", "pageUrl": "/livescores/3230799", "id": "3230799", "home": {"name": "Boston United", "id": "8646"}, "away": {"name": "Rochdale", "id": "8493"}, "status": {"finished": true, "started": true, "cancelled": false, "scoreStr": "1 : 2", "startDateStr": "Dec 17, 2019", "reason": {"short": "FT", "long": "Full-Time"}}, "firstUnplayedMatch": false}, {"monthKey": "December 18, 2019", "pageUrl": "/livescores/3230800", "id": "3230800", "home": {"name": "Plymouth Argyle", "id": "8401"}, "away": {"name": "Bristol Rovers", "id": "10104"}, "status": {"finished": true, "started": true, "cancelled": false, "scoreStr": "0 : 1", "startDateStr": "Dec 18, 2019", "reason": {"short": "FT", "long": "Full-Time"}}, "firstUnplayedMatch": false}, {"monthKey": "January 04, 2020", "pageUrl": "/livescores/3231249", "id": "3231249", "home": {"name": "Birmingham City", "id": "8658"}, "away": {"name": "Blackburn Rovers", "id": "8655"}, "status": {"finished": true, "started": true, "cancelled": false, "scoreStr": "2 : 1", "startDateStr": "Jan 4, 2020", "reason": {"short": "FT", "long": "Full-Time"}}, "firstUnplayedMatch": false}, {"monthKey": "January 04, 2020", "pageUrl": "/livescores/3231231", "id": "3231231", "home": {"name": "Bristol City", "id": "8427"}, "away": {"name": "Shrewsbury Town", "id": "9896"}, "status": {"finished": true, "started": true, "cancelled": false, "scoreStr": "1 : 1", "startDateStr": "Jan 4, 2020", "reason": {"short": "FT", "long": "Full-Time"}}, "firstUnplayedMatch": false}, {"monthKey": "January 04, 2020", "pageUrl": "/livescores/3231248", "id": "3231248", "home": {"name": "Burnley", "id": "8191"}, "away": {"name": "Peterborough United", "id": "8677"}, "status": {"finished": true, "started": true, "cancelled": false, "scoreStr": "4 : 2", "startDateStr": "Jan 4, 2020", "reason": {"short": "FT", "long": "Full-Time"}}, "firstUnplayedMatch": false}, {"monthKey": "January 04, 2020", "pageUrl": "/livescores/3231241", "id": "3231241", "home": {"name": "Millwall", "id": "10004"}, "away": {"name": "Newport County", "id": "10262"}, "status": {"finished": true, "started": true, "cancelled": false, "scoreStr": "3 : 0", "startDateStr": "Jan 4, 2020", "reason": {"short": "FT", "long": "Full-Time"}}, "firstUnplayedMatch": false}, {"monthKey": "January 04, 2020", "pageUrl": "/livescores/3231225", "id": "3231225", "home": {"name": "Rochdale", "id": "8493"}, "away": {"name": "Newcastle United", "id": "10261"}, "status": {"finished": true, "started": true, "cancelled": false, "scoreStr": "1 : 1", "startDateStr": "Jan 4, 2020", "reason": {"short": "FT", "long": "Full-Time"}}, "firstUnplayedMatch": false}, {"monthKey": "January 04, 2020", "pageUrl": "/livescores/3231250", "id": "3231250", "home": {"name": "Rotherham United", "id": "8119"}, "away": {"name": "Hull City", "id": "8667"}, "status": {"finished": true, "started": true, "cancelled": false, "scoreStr": "2 : 3", "startDateStr": "Jan 4, 2020", "reason": {"short": "FT", "long": "Full-Time"}}, "firstUnplayedMatch": false}, {"monthKey": "January 04, 2020", "pageUrl": "/livescores/3231243", "id": "3231243", "home": {"name": "Brentford", "id": "9937"}, "away": {"name": "Stoke City", "id": "10194"}, "status": {"finished": true, "started": true, "cancelled": false, "scoreStr": "1 : 0", "startDateStr": "Jan 4, 2020", "reason": {"short": "FT", "long": "Full-Time"}}, "firstUnplayedMatch": false}, {"monthKey": "January 04, 2020", "pageUrl": "/livescores/3231233", "id": "3231233", "home": {"name": "Brighton & Hove Albion", "id": "10204"}, "away": {"name": "Sheffield Wednesday", "id": "10163"}, "status": {"finished": true, "started": true, "cancelled": false, "scoreStr": "0 : 1", "startDateStr": "Jan 4, 2020", "reason": {"short": "FT", "long": "Full-Time"}}, "firstUnplayedMatch": false}, {"monthKey": "January 04, 2020", "pageUrl": "/livescores/3231226", "id": "3231226", "home": {"name": "Cardiff City", "id": "8344"}, "away": {"name": "Carlisle United", "id": "10196"}, "status": {"finished": true, "started": true, "cancelled": false, "scoreStr": "2 : 2", "startDateStr": "Jan 4, 2020", "reason": {"short": "FT", "long": "Full-Time"}}, "firstUnplayedMatch": false}, {"monthKey": "January 04, 2020", "pageUrl": "/livescores/3231221", "id": "3231221", "home": {"name": "Fulham", "id": "9879"}, "away": {"name": "Aston Villa", "id": "10252"}, "status": {"finished": true, "started": true, "cancelled": false, "scoreStr": "2 : 1", "startDateStr": "Jan 4, 2020", "reason": {"short": "FT", "long": "Full-Time"}}, "firstUnplayedMatch": false}, {"monthKey": "January 04, 2020", "pageUrl": "/livescores/3231227", "id": "3231227", "home": {"name": "Oxford United", "id": "8653"}, "away": {"name": "Hartlepool United", "id": "8488"}, "status": {"finished": true, "started": true, "cancelled": false, "scoreStr": "4 : 1", "startDateStr": "Jan 4, 2020", "reason": {"short": "FT", "long": "Full-Time"}}, "firstUnplayedMatch": false}, {"monthKey": "January 04, 2020", "pageUrl": "/livescores/3231240", "id": "3231240", "home": {"name": "Preston North End", "id": "8411"}, "away": {"name": "Norwich City", "id": "9850"}, "status": {"finished": true, "started": true, "cancelled": false, "scoreStr": "2 : 4", "startDateStr": "Jan 4, 2020", "reason": {"short": "FT", "long": "Full-Time"}}, "firstUnplayedMatch": false}, {"monthKey": "January 04, 2020", "pageUrl": "/livescores/3231238", "id": "3231238", "home": {"name": "Reading", "id": "9798"}, "away": {"name": "Blackpool", "id": "8483"}, "status": {"finished": true, "started": true, "cancelled": false, "scoreStr": "2 : 2", "startDateStr": "Jan 4, 2020", "reason": {"short": "FT", "long": "Full-Time"}}, "firstUnplayedMatch": false}, {"monthKey": "January 04, 2020", "pageUrl": "/livescores/3231229", "id": "3231229", "home": {"name": "Southampton", "id": "8466"}, "away": {"name": "Huddersfield Town", "id": "9796"}, "status": {"finished": true, "started": true, "cancelled": false, "scoreStr": "2 : 0", "startDateStr": "Jan 4, 2020", "reason": {"short": "FT", "long": "Full-Time"}}, "firstUnplayedMatch": false}, {"monthKey": "January 04, 2020", "pageUrl": "/livescores/3231239", "id": "3231239", "home": {"name": "Watford", "id": "9817"}, "away": {"name": "Tranmere Rovers", "id": "8313"}, "status": {"finished": true, "started": true, "cancelled": false, "scoreStr": "3 : 3", "startDateStr": "Jan 4, 2020", "reason": {"short": "FT", "long": "Full-Time"}}, "firstUnplayedMatch": false}, {"monthKey": "January 04, 2020", "pageUrl": "/livescores/3231232", "id": "3231232", "home": {"name": "AFC Bournemouth", "id": "8678"}, "away": {"name": "Luton Town", "id": "8346"}, "status": {"finished": true, "started": true, "cancelled": false, "scoreStr": "4 : 0", "startDateStr": "Jan 4, 2020", "reason": {"short": "FT", "long": "Full-Time"}}, "firstUnplayedMatch": false}, {"monthKey": "January 04, 2020", "pageUrl": "/livescores/3231244", "id": "3231244", "home": {"name": "Fleetwood Town", "id": "45723"}, "away": {"name": "Portsmouth", "id": "8462"}, "status": {"finished": true, "started": true, "cancelled": false, "scoreStr": "1 : 2", "startDateStr": "Jan 4, 2020", "reason": {"short": "FT", "long": "Full-Time"}}, "firstUnplayedMatch": false}, {"monthKey": "January 04, 2020", "pageUrl": "/livescores/3231219", "id": "3231219", "home": {"name": "Leicester City", "id": "8197"}, "away": {"name": "Wigan Athletic", "id": "8528"}, "status": {"finished": true, "started": true, "cancelled": false, "scoreStr": "2 : 0", "startDateStr": "Jan 4, 2020", "reason": {"short": "FT", "long": "Full-Time"}}, "firstUnplayedMatch": false}, {"monthKey": "January 04, 2020", "pageUrl": "/livescores/3231236", "id": "3231236", "home": {"name": "Manchester City", "id": "8456"}, "away": {"name": "Port Vale", "id": "9799"}, "status": {"finished": true, "started": true, "cancelled": false, "scoreStr": "4 : 1", "startDateStr": "Jan 4, 2020", "reason": {"short": "FT", "long": "Full-Time"}}, "firstUnplayedMatch": false}, {"monthKey": "January 04, 2020", "pageUrl": "/livescores/3231223", "id": "3231223", "home": {"name": "Wolverhampton Wanderers", "id": "8602"}, "away": {"name": "Manchester United", "id": "10260"}, "status": {"finished": true, "started": true, "cancelled": false, "scoreStr": "0 : 0", "startDateStr": "Jan 4, 2020", "reason": {"short": "FT", "long": "Full-Time"}}, "firstUnplayedMatch": false}, {"monthKey": "January 05, 2020", "pageUrl": "/livescores/3231234", "id": "3231234", "home": {"name": "Bristol Rovers", "id": "10104"}, "away": {"name": "Coventry City", "id": "8669"}, "status": {"finished": true, "started": true, "cancelled": false, "scoreStr": "2 : 2", "startDateStr": "Jan 5, 2020", "reason": {"short": "FT", "long": "Full-Time"}}, "firstUnplayedMatch": false}, {"monthKey": "January 05, 2020", "pageUrl": "/livescores/3231247", "id": "3231247", "home": {"name": "Burton Albion", "id": "9792"}, "away": {"name": "Northampton Town", "id": "8651"}, "status": {"finished": true, "started": true, "cancelled": false, "scoreStr": "2 : 4", "startDateStr": "Jan 5, 2020", "reason": {"short": "FT", "long": "Full-Time"}}, "firstUnplayedMatch": false}, {"monthKey": "January 05, 2020", "pageUrl": "/livescores/3231224", "id": "3231224", "home": {"name": "Charlton Athletic", "id": "8451"}, "away": {"name": "West Bromwich Albion", "id": "8659"}, "status": {"finished": true, "started": true, "cancelled": false, "scoreStr": "0 : 1", "startDateStr": "Jan 5, 2020", "reason": {"short": "FT", "long": "Full-Time"}}, "firstUnplayedMatch": false}, {"monthKey": "January 05, 2020", "pageUrl": "/livescores/3231222", "id": "3231222", "home": {"name": "Chelsea", "id": "8455"}, "away": {"name": "Nottingham Forest", "id": "10203"}, "status": {"finished": true, "started": true, "cancelled": false, "scoreStr": "2 : 0", "startDateStr": "Jan 5, 2020", "reason": {"short": "FT", "long": "Full-Time"}}, "firstUnplayedMatch": false}, {"monthKey": "January 05, 2020", "pageUrl": "/livescores/3231235", "id": "3231235", "home": {"name": "Crewe Alexandra", "id": "9784"}, "away": {"name": "Barnsley", "id": "8283"}, "status": {"finished": true, "started": true, "cancelled": false, "scoreStr": "1 : 3", "startDateStr": "Jan 5, 2020", "reason": {"short": "FT", "long": "Full-Time"}}, "firstUnplayedMatch": false}, {"monthKey": "January 05, 2020", "pageUrl": "/livescores/3231242", "id": "3231242", "home": {"name": "Crystal Palace", "id": "9826"}, "away": {"name": "Derby County", "id": "10170"}, "status": {"finished": true, "started": true, "cancelled": false, "scoreStr": "0 : 1", "startDateStr": "Jan 5, 2020", "reason": {"short": "FT", "long": "Full-Time"}}, "firstUnplayedMatch": false}, {"monthKey": "January 05, 2020", "pageUrl": "/livescores/3231237", "id": "3231237", "home": {"name": "Middlesbrough", "id": "8549"}, "away": {"name": "Tottenham Hotspur", "id": "8586"}, "status": {"finished": true, "started": true, "cancelled": false, "scoreStr": "1 : 1", "startDateStr": "Jan 5, 2020", "reason": {"short": "FT", "long": "Full-Time"}}, "firstUnplayedMatch": false}, {"monthKey": "January 05, 2020", "pageUrl": "/livescores/3231220", "id": "3231220", "home": {"name": "Queens Park Rangers", "id": "10172"}, "away": {"name": "Swansea City", "id": "10003"}, "status": {"finished": true, "started": true, "cancelled": false, "scoreStr": "5 : 1", "startDateStr": "Jan 5, 2020", "reason": {"short": "FT", "long": "Full-Time"}}, "firstUnplayedMatch": false}, {"monthKey": "January 05, 2020", "pageUrl": "/livescores/3231228", "id": "3231228", "home": {"name": "Sheffield United", "id": "8657"}, "away": {"name": "AFC Fylde", "id": "282396"}, "status": {"finished": true, "started": true, "cancelled": false, "scoreStr": "2 : 1", "startDateStr": "Jan 5, 2020", "reason": {"short": "FT", "long": "Full-Time"}}, "firstUnplayedMatch": false}, {"monthKey": "January 05, 2020", "pageUrl": "/livescores/3231230", "id": "3231230", "home": {"name": "Liverpool", "id": "8650"}, "away": {"name": "Everton", "id": "8668"}, "status": {"finished": true, "started": true, "cancelled": false, "scoreStr": "1 : 0", "startDateStr": "Jan 5, 2020", "reason": {"short": "FT", "long": "Full-Time"}}, "firstUnplayedMatch": false}, {"monthKey": "January 05, 2020", "pageUrl": "/livescores/3231246", "id": "3231246", "home": {"name": "Gillingham", "id": "10173"}, "away": {"name": "West Ham United", "id": "8654"}, "status": {"finished": true, "started": true, "cancelled": false, "scoreStr": "0 : 2", "startDateStr": "Jan 5, 2020", "reason": {"short": "FT", "long": "Full-Time"}}, "firstUnplayedMatch": false}, {"monthKey": "January 07, 2020", "pageUrl": "/livescores/3231245", "id": "3231245", "home": {"name": "Arsenal", "id": "9825"}, "away": {"name": "Leeds United", "id": "8463"}, "status": {"finished": true, "started": true, "cancelled": false, "scoreStr": "1 : 0", "startDateStr": "Jan 7, 2020", "reason": {"short": "FT", "long": "Full-Time"}}, "firstUnplayedMatch": false}, {"monthKey": "January 15, 2020", "pageUrl": "/livescores/3248458", "id": "3248458", "home": {"name": "Blackpool", "id": "8483"}, "away": {"name": "Reading", "id": "9798"}, "status": {"finished": true, "started": true, "cancelled": false, "scoreStr": "0 : 2", "startDateStr": "Jan 15, 2020", "reason": {"short": "FT", "long": "Full-Time"}}, "firstUnplayedMatch": false}, {"monthKey": "January 15, 2020", "pageUrl": "/livescores/3248959", "id": "3248959", "home": {"name": "Coventry City", "id": "8669"}, "away": {"name": "Bristol Rovers", "id": "10104"}, "status": {"finished": true, "started": true, "cancelled": false, "scoreStr": "3 : 0", "startDateStr": "Jan 15, 2020", "reason": {"short": "FT", "long": "Full-Time"}}, "firstUnplayedMatch": false}, {"monthKey": "January 15, 2020", "pageUrl": "/livescores/3248455", "id": "3248455", "home": {"name": "Newcastle United", "id": "10261"}, "away": {"name": "Rochdale", "id": "8493"}, "status": {"finished": true, "started": true, "cancelled": false, "scoreStr": "4 : 1", "startDateStr": "Jan 15, 2020", "reason": {"short": "FT", "long": "Full-Time"}}, "firstUnplayedMatch": false}, {"monthKey": "January 15, 2020", "pageUrl": "/livescores/3248456", "id": "3248456", "home": {"name": "Shrewsbury Town", "id": "9896"}, "away": {"name": "Bristol City", "id": "8427"}, "status": {"finished": true, "started": true, "cancelled": false, "scoreStr": "1 : 0", "startDateStr": "Jan 15, 2020", "reason": {"short": "FT", "long": "Full-Time"}}, "firstUnplayedMatch": false}, {"monthKey": "January 15, 2020", "pageUrl": "/livescores/3248960", "id": "3248960", "home": {"name": "Tottenham Hotspur", "id": "8586"}, "away": {"name": "Middlesbrough", "id": "8549"}, "status": {"finished": true, "started": true, "cancelled": false, "scoreStr": "2 : 1", "startDateStr": "Jan 15, 2020", "reason": {"short": "FT", "long": "Full-Time"}}, "firstUnplayedMatch": false}, {"monthKey": "January 16, 2020", "pageUrl": "/livescores/3248457", "id": "3248457", "home": {"name": "Carlisle United", "id": "10196"}, "away": {"name": "Cardiff City", "id": "8344"}, "status": {"finished": true, "started": true, "cancelled": false, "scoreStr": "3 : 4", "startDateStr": "Jan 16, 2020", "reason": {"short": "FT", "long": "Full-Time"}}, "firstUnplayedMatch": false}, {"monthKey": "January 16, 2020", "pageUrl": "/livescores/3248539", "id": "3248539", "home": {"name": "Manchester United", "id": "10260"}, "away": {"name": "Wolverhampton Wanderers", "id": "8602"}, "status": {"finished": true, "started": true, "cancelled": false, "scoreStr": "1 : 0", "startDateStr": "Jan 16, 2020", "reason": {"short": "FT", "long": "Full-Time"}}, "firstUnplayedMatch": false}, {"monthKey": "January 24, 2020", "pageUrl": "/livescores/3248459", "id": "3248459", "home": {"name": "Tranmere Rovers", "id": "8313"}, "away": {"name": "Watford", "id": "9817"}, "status": {"finished": true, "started": true, "cancelled": false, "scoreStr": "2 : 1", "startDateStr": "Jan 24, 2020", "reason": {"short": "FT", "long": "Full-Time"}}, "firstUnplayedMatch": false}, {"monthKey": "January 25, 2020", "pageUrl": "/livescores/3249677", "id": "3249677", "home": {"name": "Northampton Town", "id": "8651"}, "away": {"name": "Derby County", "id": "10170"}, "status": {"finished": true, "started": true, "cancelled": false, "scoreStr": "0 : 0", "startDateStr": "Jan 25, 2020", "reason": {"short": "FT", "long": "Full-Time"}}, "firstUnplayedMatch": false}, {"monthKey": "January 25, 2020", "pageUrl": "/livescores/3249675", "id": "3249675", "home": {"name": "Queens Park Rangers", "id": "10172"}, "away": {"name": "Sheffield Wednesday", "id": "10163"}, "status": {"finished": true, "started": true, "cancelled": false, "scoreStr": "1 : 2", "startDateStr": "Jan 25, 2020", "reason": {"short": "FT", "long": "Full-Time"}}, "firstUnplayedMatch": false}, {"monthKey": "January 25, 2020", "pageUrl": "/livescores/3249678", "id": "3249678", "home": {"name": "Brentford", "id": "9937"}, "away": {"name": "Leicester City", "id": "8197"}, "status": {"finished": true, "started": true, "cancelled": false, "scoreStr": "0 : 1", "startDateStr": "Jan 25, 2020", "reason": {"short": "FT", "long": "Full-Time"}}, "firstUnplayedMatch": false}, {"monthKey": "January 25, 2020", "pageUrl": "/livescores/3249682", "id": "3249682", "home": {"name": "Burnley", "id": "8191"}, "away": {"name": "Norwich City", "id": "9850"}, "status": {"finished": true, "started": true, "cancelled": false, "scoreStr": "1 : 2", "startDateStr": "Jan 25, 2020", "reason": {"short": "FT", "long": "Full-Time"}}, "firstUnplayedMatch": false}, {"monthKey": "January 25, 2020", "pageUrl": "/livescores/3249683", "id": "3249683", "home": {"name": "Coventry City", "id": "8669"}, "away": {"name": "Birmingham City", "id": "8658"}, "status": {"finished": true, "started": true, "cancelled": false, "scoreStr": "0 : 0", "startDateStr": "Jan 25, 2020", "reason": {"short": "FT", "long": "Full-Time"}}, "firstUnplayedMatch": false}, {"monthKey": "January 25, 2020", "pageUrl": "/livescores/3249679", "id": "3249679", "home": {"name": "Millwall", "id": "10004"}, "away": {"name": "Sheffield United", "id": "8657"}, "status": {"finished": true, "started": true, "cancelled": false, "scoreStr": "0 : 2", "startDateStr": "Jan 25, 2020", "reason": {"short": "FT", "long": "Full-Time"}}, "firstUnplayedMatch": false}, {"monthKey": "January 25, 2020", "pageUrl": "/livescores/3249685", "id": "3249685", "home": {"name": "Newcastle United", "id": "10261"}, "away": {"name": "Oxford United", "id": "8653"}, "status": {"finished": true, "started": true, "cancelled": false, "scoreStr": "0 : 0", "startDateStr": "Jan 25, 2020", "reason": {"short": "FT", "long": "Full-Time"}}, "firstUnplayedMatch": false}, {"monthKey": "January 25, 2020", "pageUrl": "/livescores/3249686", "id": "3249686", "home": {"name": "Portsmouth", "id": "8462"}, "away": {"name": "Barnsley", "id": "8283"}, "status": {"finished": true, "started": true, "cancelled": false, "scoreStr": "4 : 2", "startDateStr": "Jan 25, 2020", "reason": {"short": "FT", "long": "Full-Time"}}, "firstUnplayedMatch": false}, {"monthKey": "January 25, 2020", "pageUrl": "/livescores/3249680", "id": "3249680", "home": {"name": "Reading", "id": "9798"}, "away": {"name": "Cardiff City", "id": "8344"}, "status": {"finished": true, "started": true, "cancelled": false, "scoreStr": "1 : 1", "startDateStr": "Jan 25, 2020", "reason": {"short": "FT", "long": "Full-Time"}}, "firstUnplayedMatch": false}, {"monthKey": "January 25, 2020", "pageUrl": "/livescores/3249674", "id": "3249674", "home": {"name": "Southampton", "id": "8466"}, "away": {"name": "Tottenham Hotspur", "id": "8586"}, "status": {"finished": true, "started": true, "cancelled": false, "scoreStr": "1 : 1", "startDateStr": "Jan 25, 2020", "reason": {"short": "FT", "long": "Full-Time"}}, "firstUnplayedMatch": false}, {"monthKey": "January 25, 2020", "pageUrl": "/livescores/3249681", "id": "3249681", "home": {"name": "West Ham United", "id": "8654"}, "away": {"name": "West Bromwich Albion", "id": "8659"}, "status": {"finished": true, "started": true, "cancelled": false, "scoreStr": "0 : 1", "startDateStr": "Jan 25, 2020", "reason": {"short": "FT", "long": "Full-Time"}}, "firstUnplayedMatch": false}, {"monthKey": "January 25, 2020", "pageUrl": "/livescores/3249673", "id": "3249673", "home": {"name": "Hull City", "id": "8667"}, "away": {"name": "Chelsea", "id": "8455"}, "status": {"finished": true, "started": true, "cancelled": false, "scoreStr": "1 : 2", "startDateStr": "Jan 25, 2020", "reason": {"short": "FT", "long": "Full-Time"}}, "firstUnplayedMatch": false}, {"monthKey": "January 26, 2020", "pageUrl": "/livescores/3249684", "id": "3249684", "home": {"name": "Manchester City", "id": "8456"}, "away": {"name": "Fulham", "id": "9879"}, "status": {"finished": true, "started": true, "cancelled": false, "scoreStr": "4 : 0", "startDateStr": "Jan 26, 2020", "reason": {"short": "FT", "long": "Full-Time"}}, "firstUnplayedMatch": false}, {"monthKey": "January 26, 2020", "pageUrl": "/livescores/3249672", "id": "3249672", "home": {"name": "Tranmere Rovers", "id": "8313"}, "away": {"name": "Manchester United", "id": "10260"}, "status": {"finished": true, "started": true, "cancelled": false, "scoreStr": "0 : 6", "startDateStr": "Jan 26, 2020", "reason": {"short": "FT", "long": "Full-Time"}}, "firstUnplayedMatch": false}, {"monthKey": "January 26, 2020", "pageUrl": "/livescores/3249687", "id": "3249687", "home": {"name": "Shrewsbury Town", "id": "9896"}, "away": {"name": "Liverpool", "id": "8650"}, "status": {"finished": true, "started": true, "cancelled": false, "scoreStr": "2 : 2", "startDateStr": "Jan 26, 2020", "reason": {"short": "FT", "long": "Full-Time"}}, "firstUnplayedMatch": false}, {"monthKey": "January 28, 2020", "pageUrl": "/livescores/3249676", "id": "3249676", "home": {"name": "AFC Bournemouth", "id": "8678"}, "away": {"name": "Arsenal", "id": "9825"}, "status": {"finished": true, "started": true, "cancelled": false, "scoreStr": "1 : 2", "startDateStr": "Jan 28, 2020", "reason": {"short": "FT", "long": "Full-Time"}}, "firstUnplayedMatch": false}, {"monthKey": "February 05, 2020", "pageUrl": "/livescores/3266737", "id": "3266737", "home": {"name": "Birmingham City", "id": "8658"}, "away": {"name": "Coventry City", "id": "8669"}, "status": {"finished": true, "started": true, "cancelled": false, "scoreStr": "6 : 3", "startDateStr": "Feb 5, 2020", "reason": {"short": "FT", "long": "Full-Time"}}, "firstUnplayedMatch": false}, {"monthKey": "February 05, 2020", "pageUrl": "/livescores/3266736", "id": "3266736", "home": {"name": "Cardiff City", "id": "8344"}, "away": {"name": "Reading", "id": "9798"}, "status": {"finished": true, "started": true, "cancelled": false, "scoreStr": "4 : 7", "startDateStr": "Feb 5, 2020", "reason": {"short": "FT", "long": "Full-Time"}}, "firstUnplayedMatch": false}, {"monthKey": "February 05, 2020", "pageUrl": "/livescores/3266566", "id": "3266566", "home": {"name": "Derby County", "id": "10170"}, "away": {"name": "Northampton Town", "id": "8651"}, "status": {"finished": true, "started": true, "cancelled": false, "scoreStr": "4 : 2", "startDateStr": "Feb 5, 2020", "reason": {"short": "FT", "long": "Full-Time"}}, "firstUnplayedMatch": false}, {"monthKey": "February 05, 2020", "pageUrl": "/livescores/3267260", "id": "3267260", "home": {"name": "Liverpool", "id": "8650"}, "away": {"name": "Shrewsbury Town", "id": "9896"}, "status": {"finished": true, "started": true, "cancelled": false, "scoreStr": "1 : 0", "startDateStr": "Feb 5, 2020", "reason": {"short": "FT", "long": "Full-Time"}}, "firstUnplayedMatch": false}, {"monthKey": "February 05, 2020", "pageUrl": "/livescores/3266738", "id": "3266738", "home": {"name": "Oxford United", "id": "8653"}, "away": {"name": "Newcastle United", "id": "10261"}, "status": {"finished": true, "started": true, "cancelled": false, "scoreStr": "2 : 3", "startDateStr": "Feb 5, 2020", "reason": {"short": "FT", "long": "Full-Time"}}, "firstUnplayedMatch": false}, {"monthKey": "February 06, 2020", "pageUrl": "/livescores/3266739", "id": "3266739", "home": {"name": "Tottenham Hotspur", "id": "8586"}, "away": {"name": "Southampton", "id": "8466"}, "status": {"finished": true, "started": true, "cancelled": false, "scoreStr": "3 : 2", "startDateStr": "Feb 6, 2020", "reason": {"short": "FT", "long": "Full-Time"}}, "firstUnplayedMatch": false}, {"monthKey": "March 03, 2020", "pageUrl": "/livescores/3267737", "id": "3267737", "home": {"name": "Portsmouth", "id": "8462"}, "away": {"name": "Arsenal", "id": "9825"}, "status": {"finished": true, "started": true, "cancelled": false, "scoreStr": "0 : 2", "startDateStr": "Mar 3, 2020", "reason": {"short": "FT", "long": "Full-Time"}}, "firstUnplayedMatch": false}, {"monthKey": "March 04, 2020", "pageUrl": "/livescores/3267694", "id": "3267694", "home": {"name": "Chelsea", "id": "8455"}, "away": {"name": "Liverpool", "id": "8650"}, "status": {"finished": true, "started": true, "cancelled": false, "scoreStr": "2 : 0", "startDateStr": "Mar 4, 2020", "reason": {"short": "FT", "long": "Full-Time"}}, "firstUnplayedMatch": false}, {"monthKey": "March 04, 2020", "pageUrl": "/livescores/3267697", "id": "3267697", "home": {"name": "Reading", "id": "9798"}, "away": {"name": "Sheffield United", "id": "8657"}, "status": {"finished": true, "started": true, "cancelled": false, "scoreStr": "1 : 2", "startDateStr": "Mar 4, 2020", "reason": {"short": "FT", "long": "Full-Time"}}, "firstUnplayedMatch": false}, {"monthKey": "March 04, 2020", "pageUrl": "/livescores/3267695", "id": "3267695", "home": {"name": "West Bromwich Albion", "id": "8659"}, "away": {"name": "Newcastle United", "id": "10261"}, "status": {"finished": true, "started": true, "cancelled": false, "scoreStr": "2 : 3", "startDateStr": "Mar 4, 2020", "reason": {"short": "FT", "long": "Full-Time"}}, "firstUnplayedMatch": false}, {"monthKey": "March 05, 2020", "pageUrl": "/livescores/3267696", "id": "3267696", "home": {"name": "Leicester City", "id": "8197"}, "away": {"name": "Birmingham City", "id": "8658"}, "status": {"finished": true, "started": true, "cancelled": false, "scoreStr": "1 : 0", "startDateStr": "Mar 5, 2020", "reason": {"short": "FT", "long": "Full-Time"}}, "firstUnplayedMatch": false}, {"monthKey": "March 05, 2020", "pageUrl": "/livescores/3267698", "id": "3267698", "home": {"name": "Sheffield Wednesday", "id": "10163"}, "away": {"name": "Manchester City", "id": "8456"}, "status": {"finished": true, "started": true, "cancelled": false, "scoreStr": "0 : 1", "startDateStr": "Mar 5, 2020", "reason": {"short": "FT", "long": "Full-Time"}}, "firstUnplayedMatch": false}, {"monthKey": "March 05, 2020", "pageUrl": "/livescores/3267700", "id": "3267700", "home": {"name": "Tottenham Hotspur", "id": "8586"}, "away": {"name": "Norwich City", "id": "9850"}, "status": {"finished": true, "started": true, "cancelled": false, "scoreStr": "3 : 4", "startDateStr": "Mar 5, 2020", "reason": {"short": "FT", "long": "Full-Time"}}, "firstUnplayedMatch": false}, {"monthKey": "March 06, 2020", "pageUrl": "/livescores/3267699", "id": "3267699", "home": {"name": "Derby County", "id": "10170"}, "away": {"name": "Manchester United", "id": "10260"}, "status": {"finished": true, "started": true, "cancelled": false, "scoreStr": "0 : 3", "startDateStr": "Mar 6, 2020", "reason": {"short": "FT", "long": "Full-Time"}}, "firstUnplayedMatch": false}, {"monthKey": "June 27, 2020", "pageUrl": "/livescores/3287551", "id": "3287551", "home": {"name": "Norwich City", "id": "9850"}, "away": {"name": "Manchester United", "id": "10260"}, "status": {"finished": true, "started": true, "cancelled": false, "scoreStr": "1 : 2", "startDateStr": "Jun 27, 2020", "reason": {"short": "FT", "long": "Full-Time"}}, "firstUnplayedMatch": false}, {"monthKey": "June 28, 2020", "pageUrl": "/livescores/3287546", "id": "3287546", "home": {"name": "Sheffield United", "id": "8657"}, "away": {"name": "Arsenal", "id": "9825"}, "status": {"finished": true, "started": true, "cancelled": false, "scoreStr": "1 : 2", "startDateStr": "Jun 28, 2020", "reason": {"short": "FT", "long": "Full-Time"}}, "firstUnplayedMatch": false}, {"monthKey": "June 28, 2020", "pageUrl": "/livescores/3287548", "id": "3287548", "home": {"name": "Leicester City", "id": "8197"}, "away": {"name": "Chelsea", "id": "8455"}, "status": {"finished": true, "started": true, "cancelled": false, "scoreStr": "0 : 1", "startDateStr": "Jun 28, 2020", "reason": {"short": "FT", "long": "Full-Time"}}, "firstUnplayedMatch": false}, {"monthKey": "June 28, 2020", "pageUrl": "/livescores/3287547", "id": "3287547", "home": {"name": "Newcastle United", "id": "10261"}, "away": {"name": "Manchester City", "id": "8456"}, "status": {"finished": true, "started": true, "cancelled": false, "scoreStr": "0 : 2", "startDateStr": "Jun 28, 2020", "reason": {"short": "FT", "long": "Full-Time"}}, "firstUnplayedMatch": false}, {"monthKey": "July 19, 2020", "pageUrl": "/livescores/3354532", "id": "3354532", "home": {"name": "Arsenal", "id": "9825"}, "away": {"name": "Manchester City", "id": "8456"}, "status": {"started": false, "cancelled": false, "finished": false, "startTimeStr": "00:15", "startDateStr": "Jul 19, 2020"}, "firstUnplayedMatch": true}, {"monthKey": "July 19, 2020", "pageUrl": "/livescores/3354531", "id": "3354531", "home": {"name": "Manchester United", "id": "10260"}, "away": {"name": "Chelsea", "id": "8455"}, "status": {"started": false, "cancelled": false, "finished": false, "startTimeStr": "22:30", "startDateStr": "Jul 19, 2020"}, "firstUnplayedMatch": false}, {"monthKey": "August 02, 2020", "pageUrl": "/livescores/3354546", "id": "3354546", "home": {"name": "Arsenal/Manchester City", "id": "1163521"}, "away": {"name": "Manchester United/Chelsea", "id": "1163520"}, "status": {"started": false, "cancelled": false, "finished": false, "startTimeStr": "00:15", "startDateStr": "Aug 2, 2020"}, "firstUnplayedMatch": false}]